setup.py
lazyload/__init__.py
lazyload.egg-info/PKG-INFO
lazyload.egg-info/SOURCES.txt
lazyload.egg-info/dependency_links.txt
lazyload.egg-info/top_level.txt