Metadata-Version: 1.1
Name: lazyload
Version: 0.0.2
Summary: Force modules loaded later not to be loaded until attribute access
Home-page: https://github.com/thomasballinger/lazyload
Author: Thomas Ballinger
Author-email: thomasballinger@gmail.com
License: MIT
Platform: UNKNOWN
Classifier: Development Status :: 3 - Alpha
Classifier: Intended Audience :: Developers
Classifier: License :: OSI Approved :: MIT License
Classifier: Operating System :: POSIX
Classifier: Programming Language :: Python
Classifier: Programming Language :: Python :: 3
